README.rst
setup.py
primelist/__init__.py
primelist/primelist.py
primelist.egg-info/PKG-INFO
primelist.egg-info/SOURCES.txt
primelist.egg-info/dependency_links.txt
primelist.egg-info/requires.txt
primelist.egg-info/top_level.txt