Metadata-Version: 1.0
Name: primelist
Version: 0.1.0.0
Summary: Python library encapsulating the set of all primes as an indexed collection (optimized for small primes).
Home-page: https://github.com/lapets/primelist
Author: Andrei Lapets
Author-email: a@lapets.io
License: MIT
Platform: UNKNOWN
